arcade_squareup_api/__init__.py
arcade_squareup_api/tools/__init__.py
arcade_squareup_api/tools/request_body_schemas.py
arcade_squareup_api/wrapper_tools/AcceptDispute.json
arcade_squareup_api/wrapper_tools/AcceptDisputeLoss.json
arcade_squareup_api/wrapper_tools/AccumulateLoyaltyPoints.json
arcade_squareup_api/wrapper_tools/ActivateDomainForApplePay.json
arcade_squareup_api/wrapper_tools/AddCardToMerchant.json
arcade_squareup_api/wrapper_tools/AddGroupToCustomer.json
arcade_squareup_api/wrapper_tools/AddOrUpdateSquareOnlineSnippet.json
arcade_squareup_api/wrapper_tools/AdjustLoyaltyPoints.json
arcade_squareup_api/wrapper_tools/ApplyInventoryAdjustments.json
arcade_squareup_api/wrapper_tools/BatchUpsertCatalogObjects.json
arcade_squareup_api/wrapper_tools/BulkCreateCustomers.json
arcade_squareup_api/wrapper_tools/BulkCreateTeamMembers.json
arcade_squareup_api/wrapper_tools/BulkCreateVendors.json
arcade_squareup_api/wrapper_tools/BulkDeleteBookingCustomAttributes.json
arcade_squareup_api/wrapper_tools/BulkDeleteCustomers.json
arcade_squareup_api/wrapper_tools/BulkDeleteLocationCustomAttributes.json
arcade_squareup_api/wrapper_tools/BulkDeleteMerchantCustomAttributes.json
arcade_squareup_api/wrapper_tools/BulkDeleteOrderCustomAttributes.json
arcade_squareup_api/wrapper_tools/BulkPublishScheduledShifts.json
arcade_squareup_api/wrapper_tools/BulkRetrieveBookings.json
arcade_squareup_api/wrapper_tools/BulkRetrieveCustomers.json
arcade_squareup_api/wrapper_tools/BulkSwapSubscriptionPlan.json
arcade_squareup_api/wrapper_tools/BulkUpdateTeamMembers.json
arcade_squareup_api/wrapper_tools/BulkUpdateVendors.json
arcade_squareup_api/wrapper_tools/BulkUpsertBookingCustomAttributes.json
arcade_squareup_api/wrapper_tools/BulkUpsertCustomerAttributes.json
arcade_squareup_api/wrapper_tools/BulkUpsertLocationCustomAttributes.json
arcade_squareup_api/wrapper_tools/BulkUpsertOrderCustomAttributes.json
arcade_squareup_api/wrapper_tools/CalculateLoyaltyPoints.json
arcade_squareup_api-4.0.0.dist-info/METADATA
arcade_squareup_api-4.0.0.dist-info/WHEEL
arcade_squareup_api-4.0.0.dist-info/entry_points.txt
arcade_squareup_api-4.0.0.dist-info/licenses/LICENSE
arcade_squareup_api-4.0.0.dist-info/RECORD
